dashactyl/__init__.py
dashactyl/client.py
dashactyl/error.py
dashactyl/user.py
dashactyl.py-0.0.8.dist-info/LICENSE.txt
dashactyl.py-0.0.8.dist-info/METADATA
dashactyl.py-0.0.8.dist-info/WHEEL
dashactyl.py-0.0.8.dist-info/top_level.txt
dashactyl.py-0.0.8.dist-info/RECORD
