Metadata-Version: 2.1
Name: dashactyl.py
Version: 0.0.8
Summary: UNKNOWN
Home-page: https://github.com/Mystik-Lukas/dashactyl.py
Author: Lukas Canter
Author-email: lukascanter07@outlook.com
License: MIT
Keywords: dahsactyl
Platform: UNKNOWN
Classifier: Development Status :: 5 - Production/Stable
Classifier: Intended Audience :: Developers
Classifier: Operating System :: Microsoft :: Windows :: Windows 10
Classifier: License :: OSI Approved :: MIT License
Classifier: Programming Language :: Python :: 3
Requires-Dist: requests
